setup.py
legos/__init__.py
legos/xkcd.py
legos.xkcd.egg-info/PKG-INFO
legos.xkcd.egg-info/SOURCES.txt
legos.xkcd.egg-info/dependency_links.txt
legos.xkcd.egg-info/namespace_packages.txt
legos.xkcd.egg-info/requires.txt
legos.xkcd.egg-info/top_level.txt