Metadata-Version: 1.1
Name: legos.xkcd
Version: 0.1.1
Summary: xkcd comic fetcher plugin for Legobot
Home-page: https://github.com/bbriggs/legos.xkcd
Author: Brenton Briggs II
Author-email: UNKNOWN
License: GPLv3
Platform: UNKNOWN
Classifier: License :: OSI Approved :: GNU General Public License v3 (GPLv3)
Classifier: Programming Language :: Python :: 3
